pydialogs/__init__.py
pydialogs/dialogs.py
pydialogs-1.0.dist-info/LICENSE
pydialogs-1.0.dist-info/METADATA
pydialogs-1.0.dist-info/WHEEL
pydialogs-1.0.dist-info/entry_points.txt
pydialogs-1.0.dist-info/top_level.txt
pydialogs-1.0.dist-info/RECORD
