Metadata-Version: 2.1
Name: pydialogs
Version: 1.0
Summary: Python library for terminal-based dialogs
Home-page: https://github.com/jarvisdevlin/pydialogs
Author: jarvisdevlin
Author-email: jarvisdevil@example.com
License-File: LICENSE
